README.rst
setup.cfg
setup.py
src/pngdistill.py
src/PngDistill.egg-info/PKG-INFO
src/PngDistill.egg-info/SOURCES.txt
src/PngDistill.egg-info/dependency_links.txt
src/PngDistill.egg-info/entry_points.txt
src/PngDistill.egg-info/requires.txt
src/PngDistill.egg-info/top_level.txt