Metadata-Version: 1.1
Name: PngDistill
Version: 0.0.2
Summary: A Python Implementation of PNG Distill
Home-page: https://github.com/CrshOverride/py-png-distill
Author: Justin Niessner
Author-email: CrshOverride@gmail.com
License: MIT
Keywords: png development image optimization
Platform: UNKNOWN
Classifier: Development Status :: 3 - Alpha
Classifier: Intended Audience :: Developers
Classifier: Topic :: Multimedia :: Graphics
Classifier: Topic :: Software Development :: Libraries :: Python Modules
Classifier: License :: OSI Approved :: MIT License
Classifier: Programming Language :: Python :: 2
Classifier: Programming Language :: Python :: 2.6
Classifier: Programming Language :: Python :: 2.7
Classifier: Programming Language :: Python :: 3
Classifier: Programming Language :: Python :: 3.2
Classifier: Programming Language :: Python :: 3.3
Classifier: Programming Language :: Python :: 3.4
